lihzahrd/__init__.py
lihzahrd/errors.py
lihzahrd/timer.py
lihzahrd/world.py
lihzahrd/bestiary/__init__.py
lihzahrd/bestiary/bestiary.py
lihzahrd/chests/__init__.py
lihzahrd/chests/chest.py
lihzahrd/enums/__init__.py
lihzahrd/enums/blocktype.py
lihzahrd/enums/entitytype.py
lihzahrd/enums/itemtype.py
lihzahrd/enums/liquidtype.py
lihzahrd/enums/prefixtype.py
lihzahrd/enums/rleencoding.py
lihzahrd/enums/walltype.py
lihzahrd/fileutils/__init__.py
lihzahrd/fileutils/coordinates.py
lihzahrd/fileutils/filereader.py
lihzahrd/fileutils/pointers.py
lihzahrd/fileutils/rect.py
lihzahrd/header/__init__.py
lihzahrd/header/anglerquest.py
lihzahrd/header/anglerquestfish.py
lihzahrd/header/backgrounds.py
lihzahrd/header/bossesdefeated.py
lihzahrd/header/clouds.py
lihzahrd/header/difficulty.py
lihzahrd/header/events.py
lihzahrd/header/fourpartsplit.py
lihzahrd/header/generatorinfo.py
lihzahrd/header/invasion.py
lihzahrd/header/invasiontype.py
lihzahrd/header/lanternnight.py
lihzahrd/header/lunarevents.py
lihzahrd/header/moonphase.py
lihzahrd/header/moonstyle.py
lihzahrd/header/oldonesarmytiers.py
lihzahrd/header/party.py
lihzahrd/header/pets.py
lihzahrd/header/pillarsinfo.py
lihzahrd/header/rain.py
lihzahrd/header/sandstorm.py
lihzahrd/header/savednpcs.py
lihzahrd/header/savedoretiers.py
lihzahrd/header/shadoworbs.py
lihzahrd/header/styles.py
lihzahrd/header/time.py
lihzahrd/header/treetopvariants.py
lihzahrd/header/version.py
lihzahrd/header/worldeviltype.py
lihzahrd/items/__init__.py
lihzahrd/items/itemstack.py
lihzahrd/journeypowers/__init__.py
lihzahrd/journeypowers/journeypowers.py
lihzahrd/npcs/__init__.py
lihzahrd/npcs/mob.py
lihzahrd/npcs/npc.py
lihzahrd/pressureplates/__init__.py
lihzahrd/pressureplates/weighedpressureplate.py
lihzahrd/signs/__init__.py
lihzahrd/signs/sign.py
lihzahrd/tileentities/__init__.py
lihzahrd/tileentities/clothingdisplay.py
lihzahrd/tileentities/hatrack.py
lihzahrd/tileentities/itemframe.py
lihzahrd/tileentities/logicsensor.py
lihzahrd-3.1.1.dist-info/METADATA
lihzahrd-3.1.1.dist-info/WHEEL
lihzahrd-3.1.1.dist-info/licenses/LICENSE.txt
lihzahrd-3.1.1.dist-info/RECORD
