Metadata-Version: 2.3
Name: lihzahrd
Version: 3.1.1
Summary: Terraria world parser in Python
Project-URL: Repository, https://forge.steffo.eu/steffo/lihzahrd/
Project-URL: Documentation, https://gh.steffo.eu/lihzahrd/
Author-email: Stefano Pigozzi <me@steffo.eu>
Maintainer-email: Stefano Pigozzi <me@steffo.eu>
License-Expression: EUPL-1.2
License-File: LICENSE.txt
Keywords: game,parser,terraria
Classifier: Development Status :: 4 - Beta
Classifier: Operating System :: OS Independent
Classifier: Programming Language :: Python :: 3.6
Requires-Python: >=3.6.2
Provides-Extra: docs
Requires-Dist: sphinx-rtd-theme>=0.4.3; extra == 'docs'
Requires-Dist: sphinx>=2.2.1; extra == 'docs'
